filebrowser_downloader/__init__.py
filebrowser_downloader/downloader.py
filebrowser_downloader-0.1.1.dist-info/licenses/LICENSE
filebrowser_downloader-0.1.1.dist-info/METADATA
filebrowser_downloader-0.1.1.dist-info/WHEEL
filebrowser_downloader-0.1.1.dist-info/top_level.txt
filebrowser_downloader-0.1.1.dist-info/RECORD
