Metadata-Version: 2.4
Name: filebrowser-downloader
Version: 0.1.1
Summary: A simple Python utility to download files or entire folders recursively from Filebrowser shares.
Author: Aleks Krnjaic
License: MIT
Project-URL: Homepage, https://github.com/alek5k/filebrowser-downloader
Project-URL: Repository, https://github.com/alek5k/filebrowser-downloader
Keywords: filebrowser,downloader,files,folders
Classifier: Development Status :: 3 - Alpha
Classifier: Programming Language :: Python :: 3
Classifier: License :: OSI Approved :: MIT License
Classifier: Operating System :: OS Independent
Requires-Python: >=3.9
License-File: LICENSE
Dynamic: license-file
